pyslvs/__init__.pxd
pyslvs/__init__.py
pyslvs/bfgs.cpython-38-darwin.so
pyslvs/bfgs.pxd
pyslvs/bfgs.pyi
pyslvs/bfgs.pyx
pyslvs/collection.py
pyslvs/efd.py
pyslvs/example.py
pyslvs/expression.cpython-38-darwin.so
pyslvs/expression.pxd
pyslvs/expression.pyi
pyslvs/expression.pyx
pyslvs/expression_parser.py
pyslvs/py.typed
pyslvs/sketch_solve.pxd
pyslvs/tinycadlib.cpython-38-darwin.so
pyslvs/tinycadlib.pxd
pyslvs/tinycadlib.pyi
pyslvs/tinycadlib.pyx
pyslvs/topo_config.cpython-38-darwin.so
pyslvs/topo_config.pxd
pyslvs/topo_config.pyi
pyslvs/topo_config.pyx
pyslvs/graph/__init__.pxd
pyslvs/graph/__init__.py
pyslvs/graph/graph.cpython-38-darwin.so
pyslvs/graph/graph.pxd
pyslvs/graph/graph.pyi
pyslvs/graph/graph.pyx
pyslvs/graph/layout.cpython-38-darwin.so
pyslvs/graph/layout.pyi
pyslvs/graph/layout.pyx
pyslvs/graph/planar.cpython-38-darwin.so
pyslvs/graph/planar.pxd
pyslvs/graph/planar.pyi
pyslvs/graph/planar.pyx
pyslvs/graph/structural.cpython-38-darwin.so
pyslvs/graph/structural.pyi
pyslvs/graph/structural.pyx
pyslvs/metaheuristics/__init__.pxd
pyslvs/metaheuristics/__init__.py
pyslvs/metaheuristics/config_types.py
pyslvs/metaheuristics/de.cpython-38-darwin.so
pyslvs/metaheuristics/de.pyi
pyslvs/metaheuristics/de.pyx
pyslvs/metaheuristics/fa.cpython-38-darwin.so
pyslvs/metaheuristics/fa.pyi
pyslvs/metaheuristics/fa.pyx
pyslvs/metaheuristics/pso.cpython-38-darwin.so
pyslvs/metaheuristics/pso.pyi
pyslvs/metaheuristics/pso.pyx
pyslvs/metaheuristics/rga.cpython-38-darwin.so
pyslvs/metaheuristics/rga.pyi
pyslvs/metaheuristics/rga.pyx
pyslvs/metaheuristics/test.cpython-38-darwin.so
pyslvs/metaheuristics/test.pyi
pyslvs/metaheuristics/test.pyx
pyslvs/metaheuristics/tlbo.cpython-38-darwin.so
pyslvs/metaheuristics/tlbo.pyi
pyslvs/metaheuristics/tlbo.pyx
pyslvs/metaheuristics/utility.cpython-38-darwin.so
pyslvs/metaheuristics/utility.pxd
pyslvs/metaheuristics/utility.pyi
pyslvs/metaheuristics/utility.pyx
pyslvs/optimization/__init__.pxd
pyslvs/optimization/__init__.py
pyslvs-22.7.0.dist-info/LICENSE
pyslvs-22.7.0.dist-info/METADATA
pyslvs-22.7.0.dist-info/WHEEL
pyslvs-22.7.0.dist-info/top_level.txt
pyslvs-22.7.0.dist-info/RECORD
