Metadata-Version: 2.1
Name: pyslvs
Version: 22.7.0
Summary: Pyslvs core module. An open source planar linkage mechanism synthesis tool.
Home-page: https://github.com/KmolYuan/pyslvs
Author: Yuan Chang
Author-email: pyslvs@gmail.com
License: AGPL
Keywords: pyslvs,mechanical-engineering,2d
Classifier: Programming Language :: Python :: 3.8
Classifier: Programming Language :: Python :: 3.9
Classifier: Programming Language :: Python :: 3.10
Classifier: Programming Language :: Cython
Classifier: Topic :: Scientific/Engineering
Classifier: License :: OSI Approved :: GNU Affero General Public License v3 or later (AGPLv3+)
Classifier: Operating System :: OS Independent
Classifier: Typing :: Typed
Requires-Python: >=3.8
License-File: LICENSE
Requires-Dist: numpy
Requires-Dist: lark-parser
